[
  {
    "id": 1,
    "title": "شیم (صداگیر) لنت ترمز پژو 405 متریال",
    "size": [
      {
        "id": 0,
        "name": "width",
        "title": "عرض",
        "value": "37 میلی متر"
      },
      {
        "id": 1,
        "name": "length",
        "title": "طول",
        "value": "83 میلی متر"
      },
      {
        "id": 2,
        "name": "thinkness",
        "title": "ضخامت",
        "value": "0/5 میلی متر"
      }
    ],
    "number": "2000 عددی",
    "images": [{ "id": 0, "url": "/products/1-1.jpg" }, { "id": 1, "url": "/products/1-2.jpg" }]
  }
]
